{
    "resources": [
        {
            "name": "Component-h2-preload.js"
        },
        {
            "name": "neo-app.json"
        },
        {
            "name": "Component-preload.js",
            "merged": true
        },
        {
            "name": "model/GanttSettingConfiguration.json"
        },
        {
            "name": "model/models-dbg.js"
        },
        {
            "name": "model/models.js"
        },
        {
            "name": "Component.js"
        },
        {
            "name": "controller/SchedulingBoard.controller.js"
        },
        {
            "name": "controller/App.controller.js"
        },
        {
            "name": "controller/App-dbg.controller.js"
        },
        {
            "name": "controller/SchedulingBoard-dbg.controller.js"
        },
        {
            "name": "manifest.json"
        },
        {
            "name": "Component-dbg.js"
        },
        {
            "name": "localService/RSH_EAM_ORDER_GANTT_SRV/metadata.xml"
        },
        {
            "name": "localService/mockserver.js"
        },
        {
            "name": "localService/mockdataRelationship/C_RSHOrdersAndOperations.json"
        },
        {
            "name": "localService/mockdataRelationship/C_RSHOperationRelationships.json"
        },
        {
            "name": "localService/customMockRequests.js"
        },
        {
            "name": "localService/RSH_SB_MAINTENANCE_ORDER/metadata.xml"
        },
        {
            "name": "localService/customMockRequestsForMaintenanceOrder-dbg.js"
        },
        {
            "name": "localService/customMockRequests-dbg.js"
        },
        {
            "name": "localService/mockserver-dbg.js"
        },
        {
            "name": "localService/customMockRequestsForMaintenanceOrder.js"
        },
        {
            "name": ".project.json"
        },
        {
            "name": "resources.json",
            "merged": true
        },
        {
            "name": "view/App.view.xml"
        },
        {
            "name": "view/OperationActionSheet.fragment.xml"
        },
        {
            "name": "view/SchedulingBoard.view.xml"
        },
        {
            "name": "Component-h2-preload-dbg.js"
        },
        {
            "name": "version.json"
        },
        {
            "name": "i18n/i18n_zh_CN.properties",
            "raw": "i18n/i18n.properties"
        },
        {
            "name": "i18n/i18n_vi.properties",
            "raw": "i18n/i18n.properties"
        },
        {
            "name": "i18n/i18n_pt.properties",
            "raw": "i18n/i18n.properties"
        },
        {
            "name": "i18n/i18n_zh_TW.properties",
            "raw": "i18n/i18n.properties"
        },
        {
            "name": "i18n/i18n_en_US_sappsd.properties",
            "raw": "i18n/i18n.properties"
        },
        {
            "name": "i18n/i18n_it.properties",
            "raw": "i18n/i18n.properties"
        },
        {
            "name": "i18n/i18n_iw.properties",
            "raw": "i18n/i18n.properties"
        },
        {
            "name": "i18n/i18n_et.properties",
            "raw": "i18n/i18n.properties"
        },
        {
            "name": "i18n/i18n_kk.properties",
            "raw": "i18n/i18n.properties"
        },
        {
            "name": "i18n/i18n_de.properties",
            "raw": "i18n/i18n.properties"
        },
        {
            "name": "i18n/i18n_tr.properties",
            "raw": "i18n/i18n.properties"
        },
        {
            "name": "i18n/i18n_uk.properties",
            "raw": "i18n/i18n.properties"
        },
        {
            "name": "i18n/i18n_nl.properties",
            "raw": "i18n/i18n.properties"
        },
        {
            "name": "i18n/i18n_lv.properties",
            "raw": "i18n/i18n.properties"
        },
        {
            "name": "i18n/i18n_ms.properties",
            "raw": "i18n/i18n.properties"
        },
        {
            "name": "i18n/i18n_sl.properties",
            "raw": "i18n/i18n.properties"
        },
        {
            "name": "i18n/i18n_bg.properties",
            "raw": "i18n/i18n.properties"
        },
        {
            "name": "i18n/i18n_en.properties",
            "raw": "i18n/i18n.properties"
        },
        {
            "name": "i18n/i18n_lt.properties",
            "raw": "i18n/i18n.properties"
        },
        {
            "name": "i18n/i18n_pl.properties",
            "raw": "i18n/i18n.properties"
        },
        {
            "name": "i18n/i18n_sk.properties",
            "raw": "i18n/i18n.properties"
        },
        {
            "name": "i18n/i18n_hu.properties",
            "raw": "i18n/i18n.properties"
        },
        {
            "name": "i18n/i18n_da.properties",
            "raw": "i18n/i18n.properties"
        },
        {
            "name": "i18n/i18n_ca.properties",
            "raw": "i18n/i18n.properties"
        },
        {
            "name": "i18n/i18n.properties",
            "raw": "i18n/i18n.properties"
        },
        {
            "name": "i18n/i18n_ar.properties",
            "raw": "i18n/i18n.properties"
        },
        {
            "name": "i18n/i18n_el.properties",
            "raw": "i18n/i18n.properties"
        },
        {
            "name": "i18n/i18n_ru.properties",
            "raw": "i18n/i18n.properties"
        },
        {
            "name": "i18n/i18n_ko.properties",
            "raw": "i18n/i18n.properties"
        },
        {
            "name": "i18n/i18n_hi.properties",
            "raw": "i18n/i18n.properties"
        },
        {
            "name": "i18n/i18n_fi.properties",
            "raw": "i18n/i18n.properties"
        },
        {
            "name": "i18n/i18n_sv.properties",
            "raw": "i18n/i18n.properties"
        },
        {
            "name": "i18n/i18n_en_US_saptrc.properties",
            "raw": "i18n/i18n.properties"
        },
        {
            "name": "i18n/i18n_es.properties",
            "raw": "i18n/i18n.properties"
        },
        {
            "name": "i18n/i18n_no.properties",
            "raw": "i18n/i18n.properties"
        },
        {
            "name": "i18n/i18n_sh.properties",
            "raw": "i18n/i18n.properties"
        },
        {
            "name": "i18n/i18n_th.properties",
            "raw": "i18n/i18n.properties"
        },
        {
            "name": "i18n/i18n_cs.properties",
            "raw": "i18n/i18n.properties"
        },
        {
            "name": "i18n/i18n_ja.properties",
            "raw": "i18n/i18n.properties"
        },
        {
            "name": "i18n/i18n_hr.properties",
            "raw": "i18n/i18n.properties"
        },
        {
            "name": "i18n/i18n_fr.properties",
            "raw": "i18n/i18n.properties"
        },
        {
            "name": "i18n/i18n_ro.properties",
            "raw": "i18n/i18n.properties"
        },
        {
            "name": "readme.md"
        }
    ]
}